MANIFEST.in
README.rst
setup.py
collective/.DS_Store
collective/__init__.py
collective/__init__.pyc
collective.ptg.scrollable.egg-info/PKG-INFO
collective.ptg.scrollable.egg-info/SOURCES.txt
collective.ptg.scrollable.egg-info/dependency_links.txt
collective.ptg.scrollable.egg-info/entry_points.txt
collective.ptg.scrollable.egg-info/namespace_packages.txt
collective.ptg.scrollable.egg-info/not-zip-safe
collective.ptg.scrollable.egg-info/requires.txt
collective.ptg.scrollable.egg-info/top_level.txt
collective/ptg/.DS_Store
collective/ptg/__init__.py
collective/ptg/__init__.pyc
collective/ptg/scrollable/.DS_Store
collective/ptg/scrollable/__init__.py
collective/ptg/scrollable/__init__.pyc
collective/ptg/scrollable/configure.zcml
collective/ptg/scrollable/i18n.sh
collective/ptg/scrollable/scrollable.pt
collective/ptg/scrollable/locales/.DS_Store
collective/ptg/scrollable/resources/.DS_Store
collective/ptg/scrollable/resources/black.jpg
collective/ptg/scrollable/resources/blank.gif
collective/ptg/scrollable/resources/h30.png
collective/ptg/scrollable/resources/h300.png
collective/ptg/scrollable/resources/hori_large.png
collective/ptg/scrollable/resources/jquery.mousewheel.js
collective/ptg/scrollable/resources/jquery.slideshowify.js
collective/ptg/scrollable/resources/jquery.ui.scrollbar.js
collective/ptg/scrollable/resources/jquery.ui.scrollbar.min.js
collective/ptg/scrollable/resources/left.png
collective/ptg/scrollable/resources/left_dark.png
collective/ptg/scrollable/resources/no_style.css
collective/ptg/scrollable/resources/play_text_large.png
collective/ptg/scrollable/resources/png24-ie.png
collective/ptg/scrollable/resources/right.png
collective/ptg/scrollable/resources/right_dark.png
collective/ptg/scrollable/resources/style.css
collective/ptg/scrollable/resources/vert_large.png
collective/ptg/scrollable/resources/white.jpg
dist/collective.ptg.scrollable-0.1.zip
docs/HISTORY.txt
docs/INSTALL.txt
docs/LICENSE.GPL
docs/LICENSE.txt