Metadata-Version: 1.0
Name: collective.ptg.scrollable
Version: 0.3
Summary: scrollable gallery type for plonetruegallery
Home-page: https://github.com/collective/collective.ptg.scrollable
Author: Espen Moe-Nilssen
Author-email: espen@medialog.no
License: GPL
Keywords: plonetruegallery gallery plone addon scrollable
Platform: UNKNOWN
Classifier: Framework :: Plone
Classifier: Programming Language :: Python
